{
    "target_number": "+6285798374340",
    "report_type": ["abuse", "spam", "illegal"],
    "sender_accounts": [
        ["danarfirdhan@gmail.com", "fdex scth ovkp ygfg", "smtp.gmail.com", 587],
        ["fbfreshx12@gmail.com", "qhye ppjp elsp zst", "smtp.gmail.com", 587],
        ["fbfreshx008@gmail.com", "wnss kdnu prrq lozh", "smtp.gmail.com", 587],
        ["fbfreshx03@gmail.com", "vogr rdqs zkno gpfy", "smtp.gmail.com", 587],
        ["starterpackone01@gmail.com", "kfmo uhfe pvbq romr", "smtp.gmail.com", 587],
        ["fbfreshx11@gmail.com", "ounx ksmq xhfi mhzw", "smtp.gmail.com", 587]
    ],
    "num_reports": 150,
    "delay_per_report": 10
}
